spectralsequence_chart/__init__.py
spectralsequence_chart/chart.py
spectralsequence_chart/chart_class.py
spectralsequence_chart/chart_edge.py
spectralsequence_chart/css_colors.py
spectralsequence_chart/display_primitives.py
spectralsequence_chart/infinity.py
spectralsequence_chart/messages.py
spectralsequence_chart/page_property.py
spectralsequence_chart/serialization.py
spectralsequence_chart/signal_dict.py
spectralsequence_chart/utils.py
spectralsequence_chart/chart_elements/__init__.py
spectralsequence_chart/chart_elements/chart_class.py
spectralsequence_chart/chart_elements/chart_edge.py
spectralsequence_chart/chart_elements/chart_shape.py
spectralsequence_chart/chart_elements/chart_types.py
spectralsequence_chart/helper_classes/__init__.py
spectralsequence_chart/helper_classes/color.py
spectralsequence_chart/helper_classes/page_property.py
spectralsequence_chart/helper_classes/shape.py
spectralsequence_chart/helper_classes/signal_dict.py
spectralsequence_chart-0.0.28.dist-info/DESCRIPTION.rst
spectralsequence_chart-0.0.28.dist-info/METADATA
spectralsequence_chart-0.0.28.dist-info/RECORD
spectralsequence_chart-0.0.28.dist-info/WHEEL
spectralsequence_chart-0.0.28.dist-info/metadata.json
spectralsequence_chart-0.0.28.dist-info/top_level.txt
