Metadata-Version: 2.0
Name: spectralsequence-chart
Version: 0.0.28
Summary: A Python implementation of the spectral sequences chart API
Home-page: https://github.com/SpectralSequences/sseq
Author: Hood Chatham
Author-email: roberthoodchatham@gmail.com
License: UNKNOWN
Platform: UNKNOWN
Classifier: Programming Language :: Python :: 3
Classifier: License :: OSI Approved :: MIT License
Classifier: Operating System :: OS Independent
Requires-Python: >=3.6
